networking_h3c/__init__.py
networking_h3c/_i18n.py
networking_h3c/common/__init__.py
networking_h3c/common/config.py
networking_h3c/common/constants.py
networking_h3c/common/exceptions.py
networking_h3c/common/rest_client.py
networking_h3c/common/topics.py
networking_h3c/db/__init__.py
networking_h3c/db/h3c_l3_vxlan_db.py
networking_h3c/db/migration/__init__.py
networking_h3c/db/migration/alembic_migrations/README
networking_h3c/db/migration/alembic_migrations/__init__.py
networking_h3c/db/migration/alembic_migrations/env.py
networking_h3c/db/migration/alembic_migrations/script.py.mako
networking_h3c/db/migration/alembic_migrations/versions/7e8ea338ac23_create_tables.py
networking_h3c/db/migration/alembic_migrations/versions/HEAD
networking_h3c/db/migration/models/__init__.py
networking_h3c/db/migration/models/head.py
networking_h3c/extensions/__init__.py
networking_h3c/extensions/portextensions.py
networking_h3c/l3_router/__init__.py
networking_h3c/l3_router/h3c_l3_router_plugin.py
networking_h3c/ml2/__init__.py
networking_h3c/ml2/mechanism_h3c.py
networking_h3c/ml2/extensions/__init__.py
networking_h3c/ml2/extensions/extension_driver_h3c.py
networking_h3c/tests/__init__.py
networking_h3c/tests/base.py
networking_h3c/tests/test_networking_h3c.py
networking_h3c/tests/unit/__init__.py
networking_h3c/tests/unit/common/__init__.py
networking_h3c/tests/unit/common/test_rest_client.py
networking_h3c/tests/unit/db/__init__.py
networking_h3c/tests/unit/db/test_h3c_l3_vxlan_db.py
networking_h3c/tests/unit/extensions/__init__.py
networking_h3c/tests/unit/extensions/test_portextensions.py
networking_h3c/tests/unit/l3_router/__init__.py
networking_h3c/tests/unit/l3_router/test_h3c_l3_router_plugin.py
networking_h3c/tests/unit/ml2/__init__.py
networking_h3c/tests/unit/ml2/test_mechanism_h3c.py
networking_h3c/tests/unit/ml2/extensions/__init__.py
networking_h3c/tests/unit/ml2/extensions/test_extension_driver_h3c.py
networking_h3c-0.1.0.dist-info/DESCRIPTION.rst
networking_h3c-0.1.0.dist-info/METADATA
networking_h3c-0.1.0.dist-info/RECORD
networking_h3c-0.1.0.dist-info/WHEEL
networking_h3c-0.1.0.dist-info/entry_points.txt
networking_h3c-0.1.0.dist-info/metadata.json
networking_h3c-0.1.0.dist-info/pbr.json
networking_h3c-0.1.0.dist-info/top_level.txt
