Metadata-Version: 2.0
Name: networking-h3c
Version: 0.1.0
Summary: H3C Vendor Code for OpenStack Neutron to integrate with H3C SDN controller
Home-page: http://www.openstack.org/
Author: OpenStack
Author-email: openstack-dev@lists.openstack.org
License: UNKNOWN
Platform: UNKNOWN
Classifier: Environment :: OpenStack
Classifier: Intended Audience :: Information Technology
Classifier: Intended Audience :: System Administrators
Classifier: License :: OSI Approved :: Apache Software License
Classifier: Operating System :: POSIX :: Linux
Classifier: Programming Language :: Python
Classifier: Programming Language :: Python :: 2
Classifier: Programming Language :: Python :: 2.7
Requires-Dist: Babel (>=2.3.4)
Requires-Dist: neutron-lib (>=1.3.0)
Requires-Dist: oslo.config (>=3.22.0)
Requires-Dist: oslo.db (>=4.19.0)
Requires-Dist: oslo.i18n (>=2.1.0)
Requires-Dist: oslo.log (>=3.22.0)
Requires-Dist: oslo.messaging (>=5.19.0)
Requires-Dist: oslo.serialization (>=1.10.0)
Requires-Dist: oslo.utils (>=3.20.0)
Requires-Dist: pbr (>=2.0.0)
